README.rst
setup.py
selenium_page_adapter/__init__.py
selenium_page_adapter/adapter.py
selenium_page_adapter/descriptors.py
selenium_page_adapter.egg-info/PKG-INFO
selenium_page_adapter.egg-info/SOURCES.txt
selenium_page_adapter.egg-info/dependency_links.txt
selenium_page_adapter.egg-info/requires.txt
selenium_page_adapter.egg-info/top_level.txt