Metadata-Version: 1.1
Name: selenium-page-adapter
Version: 0.2.0
Summary: PageAdapter pattern for Python Selenium browser test abstraction.
Home-page: https://selenium_page_adapter.readthedocs.org/en/latest/
Author: Tyson Clugg
Author-email: tyson@clugg.net
License: MIT
Platform: UNKNOWN
Classifier: Development Status :: 4 - Beta
Classifier: Programming Language :: Python :: 2
Classifier: Programming Language :: Python :: 3
Classifier: License :: OSI Approved :: MIT License
Classifier: Topic :: Internet :: WWW/HTTP
Classifier: Topic :: Software Development :: Libraries
